{
  "/404": "pages/404.js",
  "/[page]": "pages/[page].js",
  "/_app": "pages/_app.js",
  "/_document": "pages/_document.js",
  "/api/hello": "pages/api/hello.js",
  "/api/homePageData": "pages/api/homePageData.js",
  "/bag": "pages/bag.js",
  "/best-selling": "pages/best-selling.js",
  "/brand/[brand]": "pages/brand/[brand].js",
  "/brands": "pages/brands.js",
  "/campaigns/[slug]": "pages/campaigns/[slug].js",
  "/campaigns": "pages/campaigns.js",
  "/campaigns/other": "pages/campaigns/other.js",
  "/campaigns/sale": "pages/campaigns/sale.js",
  "/category/[category]": "pages/category/[category].js",
  "/checkout": "pages/checkout.js",
  "/checkout/order-received/[order]": "pages/checkout/order-received/[order].js",
  "/concern/[concern]": "pages/concern/[concern].js",
  "/contact": "pages/contact.js",
  "/edit-profile": "pages/edit-profile.js",
  "/faq": "pages/faq.js",
  "/forget-password-message/[email]": "pages/forget-password-message/[email].js",
  "/forget-password": "pages/forget-password.js",
  "/": "pages/index.js",
  "/login": "pages/login.js",
  "/new": "pages/new.js",
  "/new/index_BK": "pages/new/index_BK.js",
  "/product/[slug]": "pages/product/[slug].js",
  "/profile/address/edit/[id]": "pages/profile/address/edit/[id].js",
  "/profile/address/new": "pages/profile/address/new.js",
  "/profile/addressbook": "pages/profile/addressbook.js",
  "/profile": "pages/profile.js",
  "/profile/orders": "pages/profile/orders.js",
  "/profile/refer": "pages/profile/refer.js",
  "/profile/waitlist": "pages/profile/waitlist.js",
  "/register": "pages/register.js",
  "/search/[search]": "pages/search/[search].js",
  "/test/[test]": "pages/test/[test].js",
  "/trending/[trend]": "pages/trending/[trend].js",
  "/_error": "pages/_error.js"
}